DECODER/decoder_3_to_8_bh.v
module decoder_3_to_8_bh (
    input [2:0] A,
    input E,
    output reg [7:0] Y
);
    always @(*) begin
        if (E == 1'b0) begin
            case (A)
                3'b000: Y = 8'b00000001;
                3'b001: Y = 8'b00000010;
                3'b010: Y = 8'b00000100;
                3'b011: Y = 8'b00001000;
                3'b100: Y = 8'b00010000;
                3'b101: Y = 8'b00100000;
                3'b110: Y = 8'b01000000;
                3'b111: Y = 8'b10000000;
                default: Y = 8'b00000000;
            endcase
        end else begin
            Y = 8'b00000000; // Disabled
        end
    end
endmodule

DECODER/decoder_3_to_8_tb.v
`timescale 1ns/1ps

module decoder_3_to_8_tb;
    reg [2:0] A;
    reg E;
    wire [7:0] Y;

    // Instantiate DUT (change module name if needed)
    decoder_3_to_8_bh dut (.A(A), .E(E), .Y(Y));

    // Waveform output
    initial begin
        $dumpfile("decoder_3_to_8.vcd");
        $dumpvars(0, decoder_3_to_8_tb);
    end

    initial begin
        $display("Time\tE\tA2 A1 A0\t|\tY");
        $display("---------------------------------------");

        E = 1; A = 3'b000; #10;  // Disabled
        $display("%0t\t%b\t%b %b %b\t|\t%b", $time, E, A[2], A[1], A[0], Y);

        E = 0;
        repeat (8) begin
            #10;
            $display("%0t\t%b\t%b %b %b\t|\t%b", $time, E, A[2], A[1], A[0], Y);
            A = A + 1;
        end


        $finish;
    end
endmodule

DECODER/decoder_3_to_8.vcd
$date
	Fri Oct 24 03:23:09 2025
$end
$version
	Icarus Verilog
$end
$timescale
	1ps
$end
$scope module decoder_3_to_8_tb $end
$var wire 8 ! Y [7:0] $end
$var reg 3 " A [2:0] $end
$var reg 1 # E $end
$scope module dut $end
$var wire 3 $ A [2:0] $end
$var wire 1 # E $end
$var reg 8 % Y [7:0] $end
$upscope $end
$upscope $end
$enddefinitions $end
$comment Show the parameter values. $end
$dumpall
$end
#0
$dumpvars
b0 %
b0 $
1#
b0 "
b0 !
$end
#10000
b1 !
b1 %
0#
#20000
b10 !
b10 %
b1 "
b1 $
#30000
b100 !
b100 %
b10 "
b10 $
#40000
b1000 !
b1000 %
b11 "
b11 $
#50000
b10000 !
b10000 %
b100 "
b100 $
#60000
b100000 !
b100000 %
b101 "
b101 $
#70000
b1000000 !
b1000000 %
b110 "
b110 $
#80000
b10000000 !
b10000000 %
b111 "
b111 $
#90000
b1 !
b1 %
b0 "
b0 $
